{
    "client": "Thunder Client",
    "collectionName": "BooksNode",
    "dateExported": "2023-11-20T09:01:33.084Z",
    "version": "1.1",
    "folders": [
        {
            "_id": "7203c8fc-fcce-4d19-9d6a-a85e95fcef3d",
            "name": "book",
            "containerId": "",
            "created": "2023-11-20T07:10:29.372Z",
            "sortNum": 10000
        },
        {
            "_id": "788517f8-c9a3-4824-a124-bb5df64129e6",
            "name": "category",
            "containerId": "",
            "created": "2023-11-20T07:10:29.374Z",
            "sortNum": 20000
        },
        {
            "_id": "fac242c5-30f8-45f3-aa67-23334fdba891",
            "name": "user",
            "containerId": "",
            "created": "2023-11-20T07:10:29.375Z",
            "sortNum": 30000
        }
    ],
    "requests": [
        {
            "_id": "73b9792f-6ee7-49c7-b9d7-5a5af6cad326",
            "colId": "da29ec89-0050-43ab-9ffa-e405ec0eeb2b",
            "containerId": "788517f8-c9a3-4824-a124-bb5df64129e6",
            "name": "getAllCategories",
            "url": "/",
            "method": "GET",
            "sortNum": 10000,
            "created": "2023-11-20T07:10:29.384Z",
            "modified": "2023-11-20T07:10:29.384Z",
            "headers": [],
            "params": [],
            "tests": []
        },
        {
            "_id": "f31b31d3-7c2f-42e6-9c9c-8c5b13d16f1f",
            "colId": "da29ec89-0050-43ab-9ffa-e405ec0eeb2b",
            "containerId": "fac242c5-30f8-45f3-aa67-23334fdba891",
            "name": "getUsers",
            "url": "/user",
            "method": "GET",
            "sortNum": 10000,
            "created": "2023-11-20T07:10:29.393Z",
            "modified": "2023-11-20T08:35:44.597Z",
            "headers": [],
            "params": [],
            "tests": []
        },
        {
            "_id": "92c3a31a-192e-44d1-8d77-17b775ecdac2",
            "colId": "da29ec89-0050-43ab-9ffa-e405ec0eeb2b",
            "containerId": "788517f8-c9a3-4824-a124-bb5df64129e6",
            "name": "getCategory",
            "url": "/1",
            "method": "GET",
            "sortNum": 20000,
            "created": "2023-11-20T07:10:29.385Z",
            "modified": "2023-11-20T07:10:29.385Z",
            "headers": [],
            "params": [],
            "tests": []
        },
        {
            "_id": "35586d20-cf62-42d6-a6a1-bc86fdb32857",
            "colId": "da29ec89-0050-43ab-9ffa-e405ec0eeb2b",
            "containerId": "fac242c5-30f8-45f3-aa67-23334fdba891",
            "name": "getUser",
            "url": "/1",
            "method": "GET",
            "sortNum": 20000,
            "created": "2023-11-20T07:10:29.394Z",
            "modified": "2023-11-20T07:10:29.394Z",
            "headers": [],
            "params": [],
            "tests": []
        },
        {
            "_id": "f2f335f3-975f-4cd4-b655-c662f0c26996",
            "colId": "da29ec89-0050-43ab-9ffa-e405ec0eeb2b",
            "containerId": "7203c8fc-fcce-4d19-9d6a-a85e95fcef3d",
            "name": "getAllBooks",
            "url": "/",
            "method": "GET",
            "sortNum": 30000,
            "created": "2023-11-20T07:10:29.373Z",
            "modified": "2023-11-20T07:10:29.373Z",
            "headers": [],
            "params": [],
            "tests": []
        },
        {
            "_id": "c9d2f62e-8369-4242-a230-67df128ad863",
            "colId": "da29ec89-0050-43ab-9ffa-e405ec0eeb2b",
            "containerId": "788517f8-c9a3-4824-a124-bb5df64129e6",
            "name": "getCategoryError",
            "url": "/999",
            "method": "GET",
            "sortNum": 30000,
            "created": "2023-11-20T07:10:29.386Z",
            "modified": "2023-11-20T07:10:29.386Z",
            "headers": [],
            "params": [],
            "tests": []
        },
        {
            "_id": "a4060257-9575-437e-8184-087e849c8e00",
            "colId": "da29ec89-0050-43ab-9ffa-e405ec0eeb2b",
            "containerId": "fac242c5-30f8-45f3-aa67-23334fdba891",
            "name": "getUserError",
            "url": "/1000",
            "method": "GET",
            "sortNum": 30000,
            "created": "2023-11-20T07:10:29.395Z",
            "modified": "2023-11-20T07:10:29.395Z",
            "headers": [],
            "params": [],
            "tests": []
        },
        {
            "_id": "dfa59b95-a921-4c88-8c36-484108e5b1bc",
            "colId": "da29ec89-0050-43ab-9ffa-e405ec0eeb2b",
            "containerId": "7203c8fc-fcce-4d19-9d6a-a85e95fcef3d",
            "name": "getBook",
            "url": "",
            "method": "GET",
            "sortNum": 40000,
            "created": "2023-11-20T07:10:29.374Z",
            "modified": "2023-11-20T07:10:29.374Z",
            "headers": []
        },
        {
            "_id": "913718d9-22c6-4969-b40a-ab850a037733",
            "colId": "da29ec89-0050-43ab-9ffa-e405ec0eeb2b",
            "containerId": "788517f8-c9a3-4824-a124-bb5df64129e6",
            "name": "postCategory",
            "url": "/",
            "method": "POST",
            "sortNum": 40000,
            "created": "2023-11-20T07:10:29.387Z",
            "modified": "2023-11-20T07:10:29.387Z",
            "headers": [
                {
                    "name": "Content-Type",
                    "value": "application/json"
                }
            ],
            "params": [],
            "body": {
                "type": "json",
                "raw": "{\n    \"name\": \"terror\"\n}",
                "form": []
            },
            "tests": []
        },
        {
            "_id": "bc8f1371-fe6b-4793-8c36-81a2ab5631a4",
            "colId": "da29ec89-0050-43ab-9ffa-e405ec0eeb2b",
            "containerId": "fac242c5-30f8-45f3-aa67-23334fdba891",
            "name": "postUser",
            "url": "/user",
            "method": "POST",
            "sortNum": 40000,
            "created": "2023-11-20T07:10:29.396Z",
            "modified": "2023-11-20T08:40:55.309Z",
            "headers": [
                {
                    "name": "Content-Type",
                    "value": "application/json"
                }
            ],
            "params": [],
            "body": {
                "type": "json",
                "raw": "{\n  \"username\": \"joseba15\",\n  \"email\": \"joseba15@gmail.com\",\n  \"password\": \"joseba\",\n  \"role\": \"ADMIN\"\n}",
                "form": []
            },
            "tests": []
        },
        {
            "_id": "1424ee48-7ac4-4fd6-86a2-af1ea4a8be8b",
            "colId": "da29ec89-0050-43ab-9ffa-e405ec0eeb2b",
            "containerId": "7203c8fc-fcce-4d19-9d6a-a85e95fcef3d",
            "name": "getBookError",
            "url": "",
            "method": "GET",
            "sortNum": 50000,
            "created": "2023-11-20T07:10:29.375Z",
            "modified": "2023-11-20T07:10:29.375Z",
            "headers": []
        },
        {
            "_id": "b72abd05-4519-4994-8dcc-68692cf4a536",
            "colId": "da29ec89-0050-43ab-9ffa-e405ec0eeb2b",
            "containerId": "788517f8-c9a3-4824-a124-bb5df64129e6",
            "name": "postCategoryErrorExits ",
            "url": "/",
            "method": "POST",
            "sortNum": 50000,
            "created": "2023-11-20T07:10:29.388Z",
            "modified": "2023-11-20T07:10:29.388Z",
            "headers": [
                {
                    "name": "Content-Type",
                    "value": "application/json"
                }
            ],
            "params": [],
            "body": {
                "type": "json",
                "raw": "{\n    \"name\": \"terror\"\n}",
                "form": []
            },
            "tests": []
        },
        {
            "_id": "1df8764a-f3d6-42d9-ab35-f1e74bfd1d0c",
            "colId": "da29ec89-0050-43ab-9ffa-e405ec0eeb2b",
            "containerId": "fac242c5-30f8-45f3-aa67-23334fdba891",
            "name": "postUserErrorFields",
            "url": "/",
            "method": "POST",
            "sortNum": 50000,
            "created": "2023-11-20T07:10:29.397Z",
            "modified": "2023-11-20T07:10:29.397Z",
            "headers": [],
            "params": [],
            "body": {
                "type": "json",
                "raw": "{\n  \"username\": \"pepe\",\n  \"role\": \"user\"\n}",
                "form": []
            },
            "tests": []
        },
        {
            "_id": "b031df8c-52ec-4fb8-8439-e5ea0f516676",
            "colId": "da29ec89-0050-43ab-9ffa-e405ec0eeb2b",
            "containerId": "7203c8fc-fcce-4d19-9d6a-a85e95fcef3d",
            "name": "postBook",
            "url": "/",
            "method": "POST",
            "sortNum": 60000,
            "created": "2023-11-20T07:10:29.376Z",
            "modified": "2023-11-20T07:10:29.376Z",
            "headers": [
                {
                    "name": "Content-Type",
                    "value": "application/json"
                }
            ],
            "params": [],
            "body": {
                "type": "json",
                "raw": "{\n    \"title\": \"hola\",\n    \"author\": \"pepe\",\n    \"pages\": 100,\n    \"price\": 23,\n    \"idCategory\": 1\n}",
                "form": []
            },
            "tests": []
        },
        {
            "_id": "39c460e7-3948-4bf2-b34c-25adfb5d76f3",
            "colId": "da29ec89-0050-43ab-9ffa-e405ec0eeb2b",
            "containerId": "788517f8-c9a3-4824-a124-bb5df64129e6",
            "name": "putCategory",
            "url": "/1",
            "method": "PUT",
            "sortNum": 60000,
            "created": "2023-11-20T07:10:29.389Z",
            "modified": "2023-11-20T07:10:29.389Z",
            "headers": [
                {
                    "name": "Content-Type",
                    "value": "application/json"
                }
            ],
            "params": [],
            "body": {
                "type": "json",
                "raw": "{\n    \"name\": \"terror2\"\n}",
                "form": []
            },
            "tests": []
        },
        {
            "_id": "42a1e5bd-fb35-4177-a9ce-30bbf10b9dfb",
            "colId": "da29ec89-0050-43ab-9ffa-e405ec0eeb2b",
            "containerId": "fac242c5-30f8-45f3-aa67-23334fdba891",
            "name": "postUserErrorExits",
            "url": "/",
            "method": "POST",
            "sortNum": 60000,
            "created": "2023-11-20T07:10:29.398Z",
            "modified": "2023-11-20T07:10:29.398Z",
            "headers": [],
            "params": [],
            "body": {
                "type": "json",
                "raw": "{\n  \"username\": \"joseba15\",\n  \"email\": \"joseba15@gmail.com\",\n  \"password\": \"joseba\",\n  \"role\": \"admin\"\n}",
                "form": []
            },
            "tests": []
        },
        {
            "_id": "a55a3612-c436-46c9-97b1-ae66b6baa5d0",
            "colId": "da29ec89-0050-43ab-9ffa-e405ec0eeb2b",
            "containerId": "788517f8-c9a3-4824-a124-bb5df64129e6",
            "name": "putCategoryErrorNotFound",
            "url": "/999",
            "method": "PUT",
            "sortNum": 65000,
            "created": "2023-11-20T07:10:29.390Z",
            "modified": "2023-11-20T07:10:29.390Z",
            "headers": [
                {
                    "name": "Content-Type",
                    "value": "application/json"
                }
            ],
            "params": [],
            "body": {
                "type": "json",
                "raw": "{\n    \"name\": \"terror2\"\n}",
                "form": []
            },
            "tests": []
        },
        {
            "_id": "d99d5d86-a7ea-4fb3-884c-41f356ab813e",
            "colId": "da29ec89-0050-43ab-9ffa-e405ec0eeb2b",
            "containerId": "fac242c5-30f8-45f3-aa67-23334fdba891",
            "name": "putUser",
            "url": "/1",
            "method": "PUT",
            "sortNum": 65000,
            "created": "2023-11-20T07:10:29.401Z",
            "modified": "2023-11-20T07:10:29.401Z",
            "headers": [],
            "params": [],
            "body": {
                "type": "json",
                "raw": "{\n  \"username\":\"joseba999\"\n}",
                "form": []
            },
            "tests": []
        },
        {
            "_id": "4ee61a40-a82a-4738-9efa-f3921177282f",
            "colId": "da29ec89-0050-43ab-9ffa-e405ec0eeb2b",
            "containerId": "fac242c5-30f8-45f3-aa67-23334fdba891",
            "name": "putUserErrorNotFound",
            "url": "/99999999999",
            "method": "PUT",
            "sortNum": 67500,
            "created": "2023-11-20T07:10:29.402Z",
            "modified": "2023-11-20T07:10:29.402Z",
            "headers": [],
            "params": [],
            "body": {
                "type": "json",
                "raw": "{\n  \"username\":\"joseba999\"\n}",
                "form": []
            },
            "tests": []
        },
        {
            "_id": "c4f8c72d-cba9-4468-a3b6-bfb5d6891ab1",
            "colId": "da29ec89-0050-43ab-9ffa-e405ec0eeb2b",
            "containerId": "7203c8fc-fcce-4d19-9d6a-a85e95fcef3d",
            "name": "postBookErrorExits",
            "url": "/",
            "method": "POST",
            "sortNum": 70000,
            "created": "2023-11-20T07:10:29.377Z",
            "modified": "2023-11-20T07:10:29.377Z",
            "headers": [
                {
                    "name": "Content-Type",
                    "value": "application/json"
                }
            ],
            "params": [],
            "body": {
                "type": "json",
                "raw": "{\n    \"title\": \"hola\",\n    \"author\": \"pepe\",\n    \"pages\": 100,\n    \"price\": 23,\n    \"idCategory\": 1\n}",
                "form": []
            },
            "tests": []
        },
        {
            "_id": "5a78cb3c-110c-474c-8a8f-1916f63c1ad9",
            "colId": "da29ec89-0050-43ab-9ffa-e405ec0eeb2b",
            "containerId": "fac242c5-30f8-45f3-aa67-23334fdba891",
            "name": "deleteUser",
            "url": "/user/655b1c915f84eff7ae38599b",
            "method": "DELETE",
            "sortNum": 70000,
            "created": "2023-11-20T07:10:29.399Z",
            "modified": "2023-11-20T08:58:03.641Z",
            "headers": [],
            "params": [],
            "tests": []
        },
        {
            "_id": "e2525a17-12d0-484b-af4f-539375cbf955",
            "colId": "da29ec89-0050-43ab-9ffa-e405ec0eeb2b",
            "containerId": "7203c8fc-fcce-4d19-9d6a-a85e95fcef3d",
            "name": "postBookErrorFields",
            "url": "/",
            "method": "POST",
            "sortNum": 80000,
            "created": "2023-11-20T07:10:29.378Z",
            "modified": "2023-11-20T07:10:29.378Z",
            "headers": [
                {
                    "name": "Content-Type",
                    "value": "application/json"
                }
            ],
            "params": [],
            "body": {
                "type": "json",
                "raw": "{\n    \n    \"author\": \"pepe\",\n    \"pages\": 100,\n    \"price\": 23,\n    \"idCategory\": 1\n}",
                "form": []
            },
            "tests": []
        },
        {
            "_id": "676f7b33-51a2-4f46-aead-f324cb255138",
            "colId": "da29ec89-0050-43ab-9ffa-e405ec0eeb2b",
            "containerId": "788517f8-c9a3-4824-a124-bb5df64129e6",
            "name": "deleteCategory",
            "url": "/1",
            "method": "DELETE",
            "sortNum": 80000,
            "created": "2023-11-20T07:10:29.391Z",
            "modified": "2023-11-20T07:10:29.391Z",
            "headers": [
                {
                    "name": "Content-Type",
                    "value": "application/json"
                }
            ],
            "params": [],
            "tests": []
        },
        {
            "_id": "768756f8-37c8-4b31-8675-6d29bf18b10d",
            "colId": "da29ec89-0050-43ab-9ffa-e405ec0eeb2b",
            "containerId": "fac242c5-30f8-45f3-aa67-23334fdba891",
            "name": "deleteUserErrorNotFound",
            "url": "/999999999999",
            "method": "DELETE",
            "sortNum": 80000,
            "created": "2023-11-20T07:10:29.400Z",
            "modified": "2023-11-20T07:10:29.400Z",
            "headers": [],
            "params": [],
            "tests": []
        },
        {
            "_id": "81f85dae-7167-4ae8-b1f3-11f977cd1aae",
            "colId": "da29ec89-0050-43ab-9ffa-e405ec0eeb2b",
            "containerId": "7203c8fc-fcce-4d19-9d6a-a85e95fcef3d",
            "name": "putBook",
            "url": "/1",
            "method": "PUT",
            "sortNum": 90000,
            "created": "2023-11-20T07:10:29.379Z",
            "modified": "2023-11-20T07:10:29.379Z",
            "headers": [
                {
                    "name": "Content-Type",
                    "value": "application/json"
                }
            ],
            "params": [],
            "body": {
                "type": "json",
                "raw": "{\n    \"title\": \"hola2\",\n    \"author\": \"pepito\",\n    \"pages\": 100,\n    \"price\": 23,\n    \"idCategory\": 1\n}",
                "form": []
            },
            "tests": []
        },
        {
            "_id": "936f8cf6-c189-45b0-ac78-c0e1419dd8b8",
            "colId": "da29ec89-0050-43ab-9ffa-e405ec0eeb2b",
            "containerId": "788517f8-c9a3-4824-a124-bb5df64129e6",
            "name": "deleteCategoryErrorNotFound ",
            "url": "/1",
            "method": "DELETE",
            "sortNum": 90000,
            "created": "2023-11-20T07:10:29.392Z",
            "modified": "2023-11-20T07:10:29.392Z",
            "headers": [
                {
                    "name": "Content-Type",
                    "value": "application/json"
                }
            ],
            "params": [],
            "tests": []
        },
        {
            "_id": "91da0fc1-f49c-4a47-a610-545381d395f0",
            "colId": "da29ec89-0050-43ab-9ffa-e405ec0eeb2b",
            "containerId": "7203c8fc-fcce-4d19-9d6a-a85e95fcef3d",
            "name": "putBookErrorNotFound",
            "url": "/999",
            "method": "PUT",
            "sortNum": 100000,
            "created": "2023-11-20T07:10:29.380Z",
            "modified": "2023-11-20T07:10:29.380Z",
            "headers": [
                {
                    "name": "Content-Type",
                    "value": "application/json"
                }
            ],
            "params": [],
            "body": {
                "type": "json",
                "raw": "{\n    \"title\": \"hola2\",\n    \"author\": \"pepito\",\n    \"pages\": 100,\n    \"price\": 23,\n    \"idCategory\": 1\n}",
                "form": []
            },
            "tests": []
        },
        {
            "_id": "69514759-78e4-42b0-a724-cb4f0d97ecad",
            "colId": "da29ec89-0050-43ab-9ffa-e405ec0eeb2b",
            "containerId": "7203c8fc-fcce-4d19-9d6a-a85e95fcef3d",
            "name": "deleteBook",
            "url": "/1",
            "method": "DELETE",
            "sortNum": 110000,
            "created": "2023-11-20T07:10:29.382Z",
            "modified": "2023-11-20T07:10:29.382Z",
            "headers": [
                {
                    "name": "Content-Type",
                    "value": "application/json"
                }
            ],
            "params": [],
            "tests": []
        },
        {
            "_id": "d38016bd-5a54-41ec-9f0c-099df95cd104",
            "colId": "da29ec89-0050-43ab-9ffa-e405ec0eeb2b",
            "containerId": "7203c8fc-fcce-4d19-9d6a-a85e95fcef3d",
            "name": "deleteBookErrorNotFound ",
            "url": "/1",
            "method": "DELETE",
            "sortNum": 120000,
            "created": "2023-11-20T07:10:29.383Z",
            "modified": "2023-11-20T07:10:29.383Z",
            "headers": [
                {
                    "name": "Content-Type",
                    "value": "application/json"
                }
            ],
            "params": [],
            "tests": []
        }
    ],
    "settings": {
        "options": {
            "baseUrl": "http://localhost:3000"
        }
    }
}